qtl/__init__.py
qtl/annotation.py
qtl/coloc.py
qtl/core.py
qtl/genotype.py
qtl/gtex.py
qtl/io.py
qtl/locusplot.py
qtl/map.py
qtl/norm.py
qtl/pca.py
qtl/pileup.py
qtl/plot.py
qtl/sam.py
qtl/stats.py
qtl/torus.py
qtl-0.1.10.dist-info/LICENSE
qtl-0.1.10.dist-info/METADATA
qtl-0.1.10.dist-info/WHEEL
qtl-0.1.10.dist-info/top_level.txt
qtl-0.1.10.dist-info/RECORD
