Metadata-Version: 2.1
Name: qtl
Version: 0.1.10
Summary: Utilities for analyzing and visualizing QTL data
Author-email: Francois Aguet <francois@broadinstitute.org>
Maintainer-email: Francois Aguet <francois@broadinstitute.org>
License: BSD 3-Clause License
Project-URL: Repository, https://github.com/broadinstitute/pyqtl.git
Keywords: Quantitative trait loci
Classifier: Development Status :: 4 - Beta
Classifier: Programming Language :: Python :: 3
Classifier: Intended Audience :: Science/Research
Classifier: Topic :: Scientific/Engineering :: Bio-Informatics
License-File: LICENSE
Requires-Dist: bx-python
Requires-Dist: pyBigWig
Requires-Dist: matplotlib
Requires-Dist: numpy
Requires-Dist: pandas
Requires-Dist: scipy
Requires-Dist: seaborn
